crawl4ai_cloud/__init__.py
crawl4ai_cloud/_client.py
crawl4ai_cloud/configs.py
crawl4ai_cloud/crawler.py
crawl4ai_cloud/errors.py
crawl4ai_cloud/models.py
crawl4ai_cloud_sdk-0.2.3.dist-info/METADATA
crawl4ai_cloud_sdk-0.2.3.dist-info/WHEEL
crawl4ai_cloud_sdk-0.2.3.dist-info/top_level.txt
crawl4ai_cloud_sdk-0.2.3.dist-info/RECORD
