Metadata-Version: 2.4
Name: crawl4ai-cloud-sdk
Version: 0.2.3
Summary: Lightweight cloud SDK for Crawl4AI - mirrors the OSS API
Author-email: Unclecode <unclecode@kidocode.com>
License-Expression: Apache-2.0
Project-URL: Homepage, https://api.crawl4ai.com
Project-URL: Documentation, https://api.crawl4ai.com/docs
Project-URL: Repository, https://github.com/unclecode/crawl4ai-cloud-sdk
Project-URL: Issues, https://github.com/unclecode/crawl4ai-cloud-sdk/issues
Project-URL: Discord, https://discord.gg/jP8KfhDhyN
Keywords: crawl4ai,web-scraping,crawler,cloud,api,web-crawler,scraping,markdown
Classifier: Development Status :: 4 - Beta
Classifier: Intended Audience :: Developers
Classifier: Programming Language :: Python :: 3
Classifier: Programming Language :: Python :: 3.9
Classifier: Programming Language :: Python :: 3.10
Classifier: Programming Language :: Python :: 3.11
Classifier: Programming Language :: Python :: 3.12
Classifier: Programming Language :: Python :: 3.13
Classifier: Topic :: Internet :: WWW/HTTP
Classifier: Topic :: Software Development :: Libraries :: Python Modules
Requires-Python: >=3.9
Requires-Dist: httpx>=0.27.0
Provides-Extra: dev
Requires-Dist: pytest>=8.0.0; extra == "dev"
Requires-Dist: pytest-asyncio>=0.23.0; extra == "dev"
